chess/__init__.py
chess/logging_config.py
chess/main.py
chess/storage.py
chess/controllers/__init__.py
chess/controllers/match_controller.py
chess/controllers/player_controller.py
chess/controllers/tournament_controller.py
chess/data/matches.json
chess/data/players.json
chess/data/tournaments.json
chess/models/__init__.py
chess/models/match.py
chess/models/player.py
chess/models/round.py
chess/models/tournament.py
chess/templates/tournament_report.html.j2
chess/views/__init__.py
chess/views/menu.py
chess/views/tournament_view.py
chess_tournament-0.2.13.dist-info/licenses/LICENSE
chess_tournament-0.2.13.dist-info/METADATA
chess_tournament-0.2.13.dist-info/WHEEL
chess_tournament-0.2.13.dist-info/entry_points.txt
chess_tournament-0.2.13.dist-info/top_level.txt
chess_tournament-0.2.13.dist-info/RECORD
