Metadata-Version: 2.4
Name: chess-tournament
Version: 0.2.13
Summary: A chess tournament software in Python
Author-email: Thi26 <thiiicroon@gmail.com>
License: MIT
Classifier: Development Status :: 3 - Alpha
Classifier: Intended Audience :: Developers
Classifier: Intended Audience :: End Users/Desktop
Classifier: License :: OSI Approved :: MIT License
Classifier: Programming Language :: Python :: 3
Classifier: Programming Language :: Python :: 3.8
Classifier: Programming Language :: Python :: 3.9
Classifier: Programming Language :: Python :: 3.10
Classifier: Programming Language :: Python :: 3.11
Classifier: Operating System :: OS Independent
Classifier: Topic :: Games/Entertainment :: Board Games
Classifier: Topic :: Software Development :: Libraries :: Python Modules
Requires-Python: >=3.8
License-File: LICENSE
Requires-Dist: jinja2>=3.1
Requires-Dist: flake8
Requires-Dist: flake8-html
Provides-Extra: dev
Requires-Dist: jinja2>=3.1; extra == "dev"
Requires-Dist: black; extra == "dev"
Requires-Dist: flake8; extra == "dev"
Requires-Dist: flake8-html; extra == "dev"
Requires-Dist: pytest; extra == "dev"
Requires-Dist: pytest-html; extra == "dev"
Requires-Dist: pre-commit; extra == "dev"
Dynamic: license-file
